LICENSE.txt
MANIFEST.in
README.md
README.txt
setup.py
LODField/__init__.py
LODField/fields.py
LODField/widgets.py
django_lodfield.egg-info/PKG-INFO
django_lodfield.egg-info/SOURCES.txt
django_lodfield.egg-info/dependency_links.txt
django_lodfield.egg-info/top_level.txt